{
  "0": {
    "plot": "An undercover cop and a mole in the police attempt to identify each other while infiltrating an Irish gang in South Boston.", 
    "rated": "R", 
    "language": "English, Cantonese", 
    "title": "The Departed", 
    "country": "USA, Hong Kong", 
    "writer": "William Monahan (screenplay), Alan Mak, Felix Chong", 
    "year": "2006", 
    "metascore": "86", 
    "imdb_id": "tt0407887", 
    "director": "Martin Scorsese", 
    "released": "06 Oct 2006", 
    "imdb_rating": "8.5", 
    "awards": "Won 4 Oscars. Another 90 wins & 123 nominations.", 
    "poster": "https://images-na.ssl-images-amazon.com/images/M/MV5BMTI1MTY2OTIxNV5BMl5BanBnXkFtZTYwNjQ4NjY3._V1_SX300.jpg", 
    "genre": "Crime, Drama, Thriller", 
    "actors": "Leonardo DiCaprio, Matt Damon, Jack Nicholson, Mark Wahlberg", 
    "runtime": "151 min", 
    "type": "movie", 
    "response": "True", 
    "imdb_votes": "885,411"
  }, 
  "1": {
    "plot": "Two stage magicians engage in competitive one-upmanship in an attempt to create the ultimate stage illusion.", 
    "rated": "PG-13", 
    "language": "English", 
    "title": "The Prestige", 
    "country": "USA, UK", 
    "writer": "Jonathan Nolan (screenplay), Christopher Nolan (screenplay), Christopher Priest (novel)", 
    "year": "2006", 
    "metascore": "66", 
    "imdb_id": "tt0482571", 
    "director": "Christopher Nolan", 
    "released": "20 Oct 2006", 
    "imdb_rating": "8.5", 
    "awards": "Nominated for 2 Oscars. Another 5 wins & 32 nominations.", 
    "poster": "https://images-na.ssl-images-amazon.com/images/M/MV5BMjA4NDI0MTIxNF5BMl5BanBnXkFtZTYwNTM0MzY2._V1_SX300.jpg", 
    "genre": "Drama, Mystery, Sci-Fi", 
    "actors": "Hugh Jackman, Christian Bale, Michael Caine, Piper Perabo", 
    "runtime": "130 min", 
    "type": "movie", 
    "response": "True", 
    "imdb_votes": "860,347"
  }, 
  "2": {
    "plot": "A murder inside the Louvre and clues in Da Vinci paintings lead to the discovery of a religious mystery protected by a secret society for two thousand years -- which could shake the foundations of Christianity.", 
    "rated": "PG-13", 
    "language": "English, French, Latin, Spanish", 
    "title": "The Da Vinci Code", 
    "country": "USA, Malta, France, UK", 
    "writer": "Akiva Goldsman (screenplay), Dan Brown (novel)", 
    "year": "2006", 
    "metascore": "46", 
    "imdb_id": "tt0382625", 
    "director": "Ron Howard", 
    "released": "19 May 2006", 
    "imdb_rating": "6.6", 
    "awards": "Nominated for 1 Golden Globe. Another 6 wins & 21 nominations.", 
    "poster": "https://images-na.ssl-images-amazon.com/images/M/MV5BMjIxMjQyMTc3Nl5BMl5BanBnXkFtZTcwMTA1MDUzMw@@._V1_SX300.jpg", 
    "genre": "Mystery, Thriller", 
    "actors": "Tom Hanks, Audrey Tautou, Ian McKellen, Jean Reno", 
    "runtime": "149 min", 
    "type": "movie", 
    "response": "True", 
    "imdb_votes": "317,714"
  }, 
  "3": {
    "plot": "In the falangist Spain of 1944, the bookish young stepdaughter of a sadistic army officer escapes into an eerie but captivating fantasy world.", 
    "rated": "R", 
    "language": "Spanish", 
    "title": "Pan's Labyrinth", 
    "country": "Spain, Mexico, USA", 
    "writer": "Guillermo del Toro", 
    "year": "2006", 
    "metascore": "98", 
    "imdb_id": "tt0457430", 
    "director": "Guillermo del Toro", 
    "released": "19 Jan 2007", 
    "imdb_rating": "8.2", 
    "awards": "Won 3 Oscars. Another 94 wins & 99 nominations.", 
    "poster": "https://images-na.ssl-images-amazon.com/images/M/MV5BMTU3ODg2NjQ5NF5BMl5BanBnXkFtZTcwMDEwODgzMQ@@._V1_SX300.jpg", 
    "genre": "Drama, Fantasy, War", 
    "actors": "Ivana Baquero, Sergi L\u00f3pez, Maribel Verd\u00fa, Doug Jones", 
    "runtime": "118 min", 
    "type": "movie", 
    "response": "True", 
    "imdb_votes": "475,029"
  }, 
  "4": {
    "plot": "A hot-shot race-car named Lightning McQueen gets waylaid in Radiator Springs, where he finds the true meaning of friendship and family.", 
    "rated": "G", 
    "language": "English, Italian, Japanese, Yiddish", 
    "title": "Cars", 
    "country": "USA", 
    "writer": "John Lasseter (original story by), Joe Ranft (original story by), Jorgen Klubien (original story by), Dan Fogelman (screenplay), John Lasseter (screenplay), Joe Ranft (screenplay), Kiel Murray (screenplay), Phil Lorin (screenplay), Jorgen Klubien (screenplay)", 
    "year": "2006", 
    "metascore": "73", 
    "imdb_id": "tt0317219", 
    "director": "John Lasseter, Joe Ranft", 
    "released": "09 Jun 2006", 
    "imdb_rating": "7.2", 
    "awards": "Nominated for 2 Oscars. Another 27 wins & 28 nominations.", 
    "poster": "https://images-na.ssl-images-amazon.com/images/M/MV5BMTg5NzY0MzA2MV5BMl5BanBnXkFtZTYwNDc3NTc2._V1_SX300.jpg", 
    "genre": "Animation, Adventure, Comedy", 
    "actors": "Owen Wilson, Paul Newman, Bonnie Hunt, Larry the Cable Guy", 
    "runtime": "117 min", 
    "type": "movie", 
    "response": "True", 
    "imdb_votes": "268,430"
  }, 
  "5": {
    "plot": "As the Mayan kingdom faces its decline, the rulers insist the key to prosperity is to build more temples and offer human sacrifices. Jaguar Paw, a young man captured for sacrifice, flees to avoid his fate.", 
    "rated": "R", 
    "language": "Maya", 
    "title": "Apocalypto", 
    "country": "USA", 
    "writer": "Mel Gibson, Farhad Safinia", 
    "year": "2006", 
    "metascore": "68", 
    "imdb_id": "tt0472043", 
    "director": "Mel Gibson", 
    "released": "08 Dec 2006", 
    "imdb_rating": "7.8", 
    "awards": "Nominated for 3 Oscars. Another 9 wins & 17 nominations.", 
    "poster": "https://images-na.ssl-images-amazon.com/images/M/MV5BNTM1NjYyNTY5OV5BMl5BanBnXkFtZTcwMjgwNTMzMQ@@._V1_SX300.jpg", 
    "genre": "Action, Adventure, Drama", 
    "actors": "Rudy Youngblood, Dalia Hern\u00e1ndez, Jonathan Brewer, Morris Birdyellowhead", 
    "runtime": "139 min", 
    "type": "movie", 
    "response": "True", 
    "imdb_votes": "238,174"
  }, 
  "6": {
    "plot": "King Leonidas of Sparta and a force of 300 men fight the Persians at Thermopylae in 480 B.C.", 
    "rated": "R", 
    "language": "English", 
    "title": "300", 
    "country": "USA", 
    "writer": "Zack Snyder (screenplay), Kurt Johnstad (screenplay), Michael Gordon (screenplay), Frank Miller (graphic novel), Lynn Varley (graphic novel)", 
    "year": "2006", 
    "metascore": "52", 
    "imdb_id": "tt0416449", 
    "director": "Zack Snyder", 
    "released": "09 Mar 2007", 
    "imdb_rating": "7.7", 
    "awards": "16 wins & 42 nominations.", 
    "poster": "https://images-na.ssl-images-amazon.com/images/M/MV5BMjAzNTkzNjcxNl5BMl5BanBnXkFtZTYwNDA4NjE3._V1_SX300.jpg", 
    "genre": "Action, Drama, Fantasy", 
    "actors": "Gerard Butler, Lena Headey, Dominic West, David Wenham", 
    "runtime": "117 min", 
    "type": "movie", 
    "response": "True", 
    "imdb_votes": "613,798"
  }, 
  "7": {
    "plot": "Armed with a licence to kill, Secret Agent James Bond sets out on his first mission as 007 and must defeat a weapons dealer in a high stakes game of poker at Casino Royale, but things are not what they seem.", 
    "rated": "PG-13", 
    "language": "English, French", 
    "title": "Casino Royale", 
    "country": "UK, Czech Republic, USA, Germany, Bahamas", 
    "writer": "Neal Purvis (screenplay), Robert Wade (screenplay), Paul Haggis (screenplay), Ian Fleming (novel)", 
    "year": "2006", 
    "metascore": "80", 
    "imdb_id": "tt0381061", 
    "director": "Martin Campbell", 
    "released": "17 Nov 2006", 
    "imdb_rating": "8.0", 
    "awards": "Won 1 BAFTA Film Award. Another 25 wins & 39 nominations.", 
    "poster": "https://images-na.ssl-images-amazon.com/images/M/MV5BMTM5MjI4NDExNF5BMl5BanBnXkFtZTcwMDM1MjMzMQ@@._V1_SX300.jpg", 
    "genre": "Action, Adventure, Thriller", 
    "actors": "Daniel Craig, Eva Green, Mads Mikkelsen, Judi Dench", 
    "runtime": "144 min", 
    "type": "movie", 
    "response": "True", 
    "imdb_votes": "475,914"
  }, 
  "8": {
    "plot": "A smart but sensible new graduate lands a job as an assistant to Miranda Priestly, the demanding editor-in-chief of a high fashion magazine.", 
    "rated": "PG-13", 
    "language": "English, French", 
    "title": "The Devil Wears Prada", 
    "country": "USA, France", 
    "writer": "Aline Brosh McKenna (screenplay), Lauren Weisberger (novel)", 
    "year": "2006", 
    "metascore": "62", 
    "imdb_id": "tt0458352", 
    "director": "David Frankel", 
    "released": "30 Jun 2006", 
    "imdb_rating": "6.8", 
    "awards": "Nominated for 2 Oscars. Another 16 wins & 48 nominations.", 
    "poster": "https://images-na.ssl-images-amazon.com/images/M/MV5BMTMyNjk4Njc3NV5BMl5BanBnXkFtZTcwNDkyMTEzMw@@._V1_SX300.jpg", 
    "genre": "Comedy, Drama", 
    "actors": "Meryl Streep, Anne Hathaway, Emily Blunt, Stanley Tucci", 
    "runtime": "109 min", 
    "type": "movie", 
    "response": "True", 
    "imdb_votes": "290,735"
  }, 
  "9": {
    "plot": "Private Joe Bauers, the definition of \"average American\", is selected by the Pentagon to be the guinea pig for a top-secret hibernation program. Forgotten, he awakes five centuries in the future. He discovers a society so incredibly dumbed down that he's easily the most intelligent person alive.", 
    "rated": "R", 
    "language": "English", 
    "title": "Idiocracy", 
    "country": "USA", 
    "writer": "Mike Judge (story), Mike Judge (screenplay), Etan Cohen (screenplay)", 
    "year": "2006", 
    "metascore": "66", 
    "imdb_id": "tt0387808", 
    "director": "Mike Judge", 
    "released": "25 Jan 2007", 
    "imdb_rating": "6.6", 
    "awards": "1 nomination.", 
    "poster": "https://images-na.ssl-images-amazon.com/images/M/MV5BMWQ4MzI2ZDQtYjk3MS00ODdjLTkwN2QtOTBjYzIwM2RmNzgyXkEyXkFqcGdeQXVyMTQxNzMzNDI@._V1_SX300.jpg", 
    "genre": "Adventure, Comedy, Sci-Fi", 
    "actors": "Luke Wilson, Maya Rudolph, Dax Shepard, Terry Crews", 
    "runtime": "84 min", 
    "type": "movie", 
    "response": "True", 
    "imdb_votes": "110,276"
  }, 
  "10": {
    "plot": "A suburban American family is being stalked by a group of psychotic people who live in the desert, far away from civilization.", 
    "rated": "R", 
    "language": "English", 
    "title": "The Hills Have Eyes", 
    "country": "USA", 
    "writer": "Alexandre Aja (screenplay), Gr\u00e9gory Levasseur (screenplay), Wes Craven", 
    "year": "2006", 
    "metascore": "52", 
    "imdb_id": "tt0454841", 
    "director": "Alexandre Aja", 
    "released": "10 Mar 2006", 
    "imdb_rating": "6.4", 
    "awards": "2 wins & 7 nominations.", 
    "poster": "https://images-na.ssl-images-amazon.com/images/M/MV5BMzk0MTg5MzEyOF5BMl5BanBnXkFtZTcwNDUyMzIzMQ@@._V1_SX300.jpg", 
    "genre": "Horror", 
    "actors": "Aaron Stanford, Kathleen Quinlan, Vinessa Shaw, Emilie de Ravin", 
    "runtime": "107 min", 
    "type": "movie", 
    "response": "True", 
    "imdb_votes": "132,565"
  }, 
  "11": {
    "plot": "A woman goes in search for her daughter within the confines of a strange, desolate town called Silent Hill.", 
    "rated": "R", 
    "language": "English", 
    "title": "Silent Hill", 
    "country": "Canada, France, Japan", 
    "writer": "Roger Avary", 
    "year": "2006", 
    "metascore": "30", 
    "imdb_id": "tt0384537", 
    "director": "Christophe Gans", 
    "released": "21 Apr 2006", 
    "imdb_rating": "6.6", 
    "awards": "8 nominations.", 
    "poster": "https://images-na.ssl-images-amazon.com/images/M/MV5BMTI4NzQ3NTgxNV5BMl5BanBnXkFtZTcwMTMwOTIzMQ@@._V1_SX300.jpg", 
    "genre": "Adventure, Horror, Mystery", 
    "actors": "Radha Mitchell, Sean Bean, Laurie Holden, Deborah Kara Unger", 
    "runtime": "125 min", 
    "type": "movie", 
    "response": "True", 
    "imdb_votes": "174,674"
  }, 
  "12": {
    "plot": "In 2027, in a chaotic world in which women have become somehow infertile, a former activist agrees to help transport a miraculously pregnant woman to a sanctuary at sea.", 
    "rated": "R", 
    "language": "English, German, Italian, Romanian, Spanish, Arabic, Georgian, Russian, Serbian", 
    "title": "Children of Men", 
    "country": "USA, UK", 
    "writer": "Alfonso Cuar\u00f3n (screenplay), Timothy J. Sexton (screenplay), David Arata (screenplay), Mark Fergus (screenplay), Hawk Ostby (screenplay), P.D. James (novel)", 
    "year": "2006", 
    "metascore": "84", 
    "imdb_id": "tt0206634", 
    "director": "Alfonso Cuar\u00f3n", 
    "released": "05 Jan 2007", 
    "imdb_rating": "7.9", 
    "awards": "Nominated for 3 Oscars. Another 41 wins & 71 nominations.", 
    "poster": "https://images-na.ssl-images-amazon.com/images/M/MV5BNDcxNTVjYTUtZjM4MS00ZWIwLTk5OGMtMWY2MjlmMzg1N2E1XkEyXkFqcGdeQXVyNDk3NzU2MTQ@._V1_SX300.jpg", 
    "genre": "Drama, Sci-Fi, Thriller", 
    "actors": "Clive Owen, Juan Gabriel Yacuzzi, Michael Caine, Mishal Husain", 
    "runtime": "109 min", 
    "type": "movie", 
    "response": "True", 
    "imdb_votes": "366,102"
  }, 
  "13": {
    "plot": "Jack Sparrow races to recover the heart of Davy Jones to avoid enslaving his soul to Jones' service, as other friends and foes seek the heart for their own agenda as well.", 
    "rated": "PG-13", 
    "language": "English, Turkish, Greek, Mandarin, French", 
    "title": "Pirates of the Caribbean: Dead Man's Chest", 
    "country": "USA", 
    "writer": "Ted Elliott, Terry Rossio, Ted Elliott (characters), Terry Rossio (characters), Stuart Beattie (characters), Jay Wolpert (characters)", 
    "year": "2006", 
    "metascore": "53", 
    "imdb_id": "tt0383574", 
    "director": "Gore Verbinski", 
    "released": "07 Jul 2006", 
    "imdb_rating": "7.3", 
    "awards": "Won 1 Oscar. Another 42 wins & 51 nominations.", 
    "poster": "https://images-na.ssl-images-amazon.com/images/M/MV5BMTcwODc1MTMxM15BMl5BanBnXkFtZTYwMDg1NzY3._V1_SX300.jpg", 
    "genre": "Action, Adventure, Fantasy", 
    "actors": "Johnny Depp, Orlando Bloom, Keira Knightley, Jack Davenport", 
    "runtime": "151 min", 
    "type": "movie", 
    "response": "True", 
    "imdb_votes": "527,196"
  }, 
  "14": {
    "plot": "In 1984 East Berlin, an agent of the secret police, conducting surveillance on a writer and his lover, finds himself becoming increasingly absorbed by their lives.", 
    "rated": "R", 
    "language": "German", 
    "title": "The Lives of Others", 
    "country": "Germany", 
    "writer": "Florian Henckel von Donnersmarck", 
    "year": "2006", 
    "metascore": "89", 
    "imdb_id": "tt0405094", 
    "director": "Florian Henckel von Donnersmarck", 
    "released": "30 Mar 2007", 
    "imdb_rating": "8.5", 
    "awards": "Won 1 Oscar. Another 75 wins & 32 nominations.", 
    "poster": "https://images-na.ssl-images-amazon.com/images/M/MV5BNDUzNjYwNDYyNl5BMl5BanBnXkFtZTcwNjU3ODQ0MQ@@._V1_SX300.jpg", 
    "genre": "Drama, Thriller", 
    "actors": "Martina Gedeck, Ulrich M\u00fche, Sebastian Koch, Ulrich Tukur", 
    "runtime": "137 min", 
    "type": "movie", 
    "response": "True", 
    "imdb_votes": "264,025"
  }, 
  "15": {
    "plot": "Three teens discover that their neighbor's house is really a living, breathing, scary monster.", 
    "rated": "PG", 
    "language": "English", 
    "title": "Monster House", 
    "country": "USA", 
    "writer": "Dan Harmon (screenplay), Rob Schrab (screenplay), Pamela Pettler (screenplay), Dan Harmon (story), Rob Schrab (story)", 
    "year": "2006", 
    "metascore": "68", 
    "imdb_id": "tt0385880", 
    "director": "Gil Kenan", 
    "released": "21 Jul 2006", 
    "imdb_rating": "6.6", 
    "awards": "Nominated for 1 Oscar. Another 4 wins & 23 nominations.", 
    "poster": "https://images-na.ssl-images-amazon.com/images/M/MV5BMTIzNjE1NDg1N15BMl5BanBnXkFtZTcwOTg2NTMzMQ@@._V1_SX300.jpg", 
    "genre": "Animation, Comedy, Family", 
    "actors": "Ryan Newman, Steve Buscemi, Mitchel Musso, Catherine O'Hara", 
    "runtime": "91 min", 
    "type": "movie", 
    "response": "True", 
    "imdb_votes": "72,927"
  }, 
  "16": {
    "plot": "A drama based on the life of Jesse James Hollywood, a drug dealer who became one of the youngest men ever to be on the FBI's most wanted list.", 
    "rated": "R", 
    "language": "English", 
    "title": "Alpha Dog", 
    "country": "USA, Germany", 
    "writer": "Nick Cassavetes", 
    "year": "2006", 
    "metascore": "53", 
    "imdb_id": "tt0426883", 
    "director": "Nick Cassavetes", 
    "released": "12 Jan 2007", 
    "imdb_rating": "6.9", 
    "awards": "1 win & 3 nominations.", 
    "poster": "https://images-na.ssl-images-amazon.com/images/M/MV5BMjExODMyNzQzMl5BMl5BanBnXkFtZTYwNzMwNTg3._V1_SX300.jpg", 
    "genre": "Biography, Crime, Drama", 
    "actors": "Bruce Willis, Matthew Barry, Emile Hirsch, Fernando Vargas", 
    "runtime": "122 min", 
    "type": "movie", 
    "response": "True", 
    "imdb_votes": "88,622"
  }, 
  "17": {
    "plot": "The retelling of France's iconic but ill-fated queen, Marie Antoinette. From her betrothal and marriage to Louis XVI at 15 to her reign as queen at 19 and to the end of her reign as queen and ultimately the fall of Versailles.", 
    "rated": "PG-13", 
    "language": "English, Latin, French", 
    "title": "Marie Antoinette", 
    "country": "USA, France, Japan", 
    "writer": "Sofia Coppola", 
    "year": "2006", 
    "metascore": "65", 
    "imdb_id": "tt0422720", 
    "director": "Sofia Coppola", 
    "released": "20 Oct 2006", 
    "imdb_rating": "6.4", 
    "awards": "Won 1 Oscar. Another 15 wins & 20 nominations.", 
    "poster": "https://images-na.ssl-images-amazon.com/images/M/MV5BMTIzOTk1NzY5NV5BMl5BanBnXkFtZTcwOTMzNDgzMQ@@._V1_SX300.jpg", 
    "genre": "Biography, Drama, History", 
    "actors": "Kirsten Dunst, Jason Schwartzman, Judy Davis, Rip Torn", 
    "runtime": "123 min", 
    "type": "movie", 
    "response": "True", 
    "imdb_votes": "80,950"
  }, 
  "18": {
    "plot": "Superman reappears after a long absence, but is challenged by an old foe who uses Kryptonian technology for world domination.", 
    "rated": "PG-13", 
    "language": "English, German, French", 
    "title": "Superman Returns", 
    "country": "USA", 
    "writer": "Michael Dougherty (screenplay), Dan Harris (screenplay), Bryan Singer (story), Michael Dougherty (story), Dan Harris (story), Jerry Siegel (characters), Joe Shuster (characters)", 
    "year": "2006", 
    "metascore": "72", 
    "imdb_id": "tt0348150", 
    "director": "Bryan Singer", 
    "released": "28 Jun 2006", 
    "imdb_rating": "6.1", 
    "awards": "Nominated for 1 Oscar. Another 12 wins & 38 nominations.", 
    "poster": "https://images-na.ssl-images-amazon.com/images/M/MV5BMTU3NzA5MjI0Nl5BMl5BanBnXkFtZTcwMTEwNzMzMQ@@._V1_SX300.jpg", 
    "genre": "Action, Adventure, Sci-Fi", 
    "actors": "Brandon Routh, Kate Bosworth, Kevin Spacey, James Marsden", 
    "runtime": "154 min", 
    "type": "movie", 
    "response": "True", 
    "imdb_votes": "241,764"
  }, 
  "19": {
    "plot": "A teenager becomes a major competitor in the world of drift racing after moving in with his father in Tokyo to avoid a jail sentence in America.", 
    "rated": "PG-13", 
    "language": "English, Japanese", 
    "title": "The Fast and the Furious: Tokyo Drift", 
    "country": "USA", 
    "writer": "Chris Morgan", 
    "year": "2006", 
    "metascore": "46", 
    "imdb_id": "tt0463985", 
    "director": "Justin Lin", 
    "released": "16 Jun 2006", 
    "imdb_rating": "6.0", 
    "awards": "4 nominations.", 
    "poster": "https://images-na.ssl-images-amazon.com/images/M/MV5BMTQ2NTMxODEyNV5BMl5BanBnXkFtZTcwMDgxMjA0MQ@@._V1_SX300.jpg", 
    "genre": "Action, Crime, Thriller", 
    "actors": "Lucas Black, Damien Marzette, Trula M. Marcus, Zachery Ty Bryan", 
    "runtime": "104 min", 
    "type": "movie", 
    "response": "True", 
    "imdb_votes": "182,119"
  }, 
  "20": {
    "plot": "A family determined to get their young daughter into the finals of a beauty pageant take a cross-country trip in their VW bus.", 
    "rated": "R", 
    "language": "English", 
    "title": "Little Miss Sunshine", 
    "country": "USA", 
    "writer": "Michael Arndt", 
    "year": "2006", 
    "metascore": "80", 
    "imdb_id": "tt0449059", 
    "director": "Jonathan Dayton, Valerie Faris", 
    "released": "18 Aug 2006", 
    "imdb_rating": "7.8", 
    "awards": "Won 2 Oscars. Another 68 wins & 104 nominations.", 
    "poster": "https://images-na.ssl-images-amazon.com/images/M/MV5BMTgzNTgzODU0NV5BMl5BanBnXkFtZTcwMjEyMjMzMQ@@._V1_SX300.jpg", 
    "genre": "Comedy, Drama", 
    "actors": "Abigail Breslin, Greg Kinnear, Paul Dano, Alan Arkin", 
    "runtime": "101 min", 
    "type": "movie", 
    "response": "True", 
    "imdb_votes": "360,416"
  }, 
  "21": {
    "plot": "In turn-of-the-century Vienna, a magician uses his abilities to secure the love of a woman far above his social standing.", 
    "rated": "PG-13", 
    "language": "English", 
    "title": "The Illusionist", 
    "country": "USA, Czech Republic", 
    "writer": "Neil Burger (screenplay), Steven Millhauser (short story \"Eisenheim the Illusionist\")", 
    "year": "2006", 
    "metascore": "68", 
    "imdb_id": "tt0443543", 
    "director": "Neil Burger", 
    "released": "01 Sep 2006", 
    "imdb_rating": "7.6", 
    "awards": "Nominated for 1 Oscar. Another 10 wins & 9 nominations.", 
    "poster": "https://images-na.ssl-images-amazon.com/images/M/MV5BMTM1MjQyMDkzN15BMl5BanBnXkFtZTcwNzAyNTQzMQ@@._V1_SX300.jpg", 
    "genre": "Drama, Mystery, Romance", 
    "actors": "Edward Norton, Paul Giamatti, Jessica Biel, Rufus Sewell", 
    "runtime": "110 min", 
    "type": "movie", 
    "response": "True", 
    "imdb_votes": "298,510"
  }, 
  "22": {
    "plot": "A fisherman, a smuggler, and a syndicate of businessmen match wits over the possession of a priceless diamond.", 
    "rated": "R", 
    "language": "English, Mende, Afrikaans", 
    "title": "Blood Diamond", 
    "country": "Germany, USA", 
    "writer": "Charles Leavitt (screenplay), Charles Leavitt (story), C. Gaby Mitchell (story)", 
    "year": "2006", 
    "metascore": "64", 
    "imdb_id": "tt0450259", 
    "director": "Edward Zwick", 
    "released": "08 Dec 2006", 
    "imdb_rating": "8.0", 
    "awards": "Nominated for 5 Oscars. Another 8 wins & 26 nominations.", 
    "poster": "https://images-na.ssl-images-amazon.com/images/M/MV5BMTY5MTYyNjkwNV5BMl5BanBnXkFtZTcwODE3MTI0MQ@@._V1_SX300.jpg", 
    "genre": "Adventure, Drama, Thriller", 
    "actors": "Leonardo DiCaprio, Djimon Hounsou, Jennifer Connelly, Kagiso Kuypers", 
    "runtime": "143 min", 
    "type": "movie", 
    "response": "True", 
    "imdb_votes": "405,102"
  }, 
  "23": {
    "plot": "When a cure is found to treat mutations, lines are drawn amongst the X-Men, led by Professor Charles Xavier, and the Brotherhood, a band of powerful mutants organized under Xavier's former ally, Magneto.", 
    "rated": "PG-13", 
    "language": "English", 
    "title": "X-Men: The Last Stand", 
    "country": "Canada, USA, UK", 
    "writer": "Simon Kinberg, Zak Penn", 
    "year": "2006", 
    "metascore": "58", 
    "imdb_id": "tt0376994", 
    "director": "Brett Ratner", 
    "released": "26 May 2006", 
    "imdb_rating": "6.8", 
    "awards": "7 wins & 37 nominations.", 
    "poster": "https://images-na.ssl-images-amazon.com/images/M/MV5BMjI1NTg2ODA2Nl5BMl5BanBnXkFtZTcwMDc2MjEzMw@@._V1_SX300.jpg", 
    "genre": "Action, Adventure, Fantasy", 
    "actors": "Hugh Jackman, Halle Berry, Ian McKellen, Patrick Stewart", 
    "runtime": "104 min", 
    "type": "movie", 
    "response": "True", 
    "imdb_votes": "387,463"
  }, 
  "24": {
    "plot": "In Venice Beach, naive Midwesterner JB bonds with local slacker KG and they form the rock band Tenacious D. Setting out to become the world's greatest band is no easy feat, so they set out to steal what could be the answer to their prayers -- a magical guitar pick housed in a rock-and-roll museum some 300 miles away.", 
    "rated": "R", 
    "language": "English", 
    "title": "Tenacious D in The Pick of Destiny", 
    "country": "USA, Germany", 
    "writer": "Jack Black, Kyle Gass, Liam Lynch", 
    "year": "2006", 
    "metascore": "55", 
    "imdb_id": "tt0365830", 
    "director": "Liam Lynch", 
    "released": "22 Nov 2006", 
    "imdb_rating": "6.8", 
    "awards": "2 nominations.", 
    "poster": "https://images-na.ssl-images-amazon.com/images/M/MV5BMTUyMDA3OTc4MV5BMl5BanBnXkFtZTcwNzE5NjkzMQ@@._V1_SX300.jpg", 
    "genre": "Adventure, Comedy, Music", 
    "actors": "Jack Black, Kyle Gass, JR Reed, Ronnie James Dio", 
    "runtime": "93 min", 
    "type": "movie", 
    "response": "True", 
    "imdb_votes": "86,617"
  }, 
  "25": {
    "plot": "A struggling salesman takes custody of his son as he's poised to begin a life-changing professional endeavor.", 
    "rated": "PG-13", 
    "language": "English, Cantonese", 
    "title": "The Pursuit of Happyness", 
    "country": "USA", 
    "writer": "Steve Conrad", 
    "year": "2006", 
    "metascore": "64", 
    "imdb_id": "tt0454921", 
    "director": "Gabriele Muccino", 
    "released": "15 Dec 2006", 
    "imdb_rating": "8.0", 
    "awards": "Nominated for 1 Oscar. Another 11 wins & 24 nominations.", 
    "poster": "https://images-na.ssl-images-amazon.com/images/M/MV5BMTQ5NjQ0NDI3NF5BMl5BanBnXkFtZTcwNDI0MjEzMw@@._V1_SX300.jpg", 
    "genre": "Biography, Drama", 
    "actors": "Will Smith, Jaden Smith, Thandie Newton, Brian Howe", 
    "runtime": "117 min", 
    "type": "movie", 
    "response": "True", 
    "imdb_votes": "343,656"
  }, 
  "26": {
    "plot": "After a ferry is bombed in New Orleans, an A.T.F. agent joins a unique investigation using experimental surveillance technology to find the bomber, but soon finds himself becoming obsessed with one of the victims.", 
    "rated": "PG-13", 
    "language": "English", 
    "title": "Deja Vu", 
    "country": "USA, UK", 
    "writer": "Bill Marsilii, Terry Rossio", 
    "year": "2006", 
    "metascore": "59", 
    "imdb_id": "tt0453467", 
    "director": "Tony Scott", 
    "released": "22 Nov 2006", 
    "imdb_rating": "7.0", 
    "awards": "1 win & 5 nominations.", 
    "poster": "https://images-na.ssl-images-amazon.com/images/M/MV5BZWUyNzk1OTEtODhlZC00NGMwLTk5MWMtZGY0YTIwMmY0MjFmXkEyXkFqcGdeQXVyNDk3NzU2MTQ@._V1_SX300.jpg", 
    "genre": "Action, Sci-Fi, Thriller", 
    "actors": "Denzel Washington, Paula Patton, Val Kilmer, Jim Caviezel", 
    "runtime": "126 min", 
    "type": "movie", 
    "response": "True", 
    "imdb_votes": "245,518"
  }, 
  "27": {
    "plot": "In this third installment of the Final Destination series, a student's premonition of a deadly rollercoaster ride saves her life and a lucky few, but not from death itself which seeks out those who escaped their fate.", 
    "rated": "R", 
    "language": "English", 
    "title": "Final Destination 3", 
    "country": "Germany, USA, Canada", 
    "writer": "Glen Morgan, James Wong, Jeffrey Reddick (characters)", 
    "year": "2006", 
    "metascore": "41", 
    "imdb_id": "tt0414982", 
    "director": "James Wong", 
    "released": "10 Feb 2006", 
    "imdb_rating": "5.8", 
    "awards": "6 nominations.", 
    "poster": "https://images-na.ssl-images-amazon.com/images/M/MV5BMTg2MzI0MzczOF5BMl5BanBnXkFtZTcwNzAyODExMw@@._V1_SX300.jpg", 
    "genre": "Horror", 
    "actors": "Mary Elizabeth Winstead, Ryan Merriman, Kris Lemche, Alexz Johnson", 
    "runtime": "93 min", 
    "type": "movie", 
    "response": "True", 
    "imdb_votes": "104,489"
  }, 
  "28": {
    "plot": "Two women troubled with guy-problems swap homes in each other's countries, where they each meet a local guy and fall in love.", 
    "rated": "PG-13", 
    "language": "English", 
    "title": "The Holiday", 
    "country": "USA", 
    "writer": "Nancy Meyers", 
    "year": "2006", 
    "metascore": "52", 
    "imdb_id": "tt0457939", 
    "director": "Nancy Meyers", 
    "released": "08 Dec 2006", 
    "imdb_rating": "6.9", 
    "awards": "2 wins & 7 nominations.", 
    "poster": "https://images-na.ssl-images-amazon.com/images/M/MV5BMTM2MzEyNDkxNF5BMl5BanBnXkFtZTcwODE5NjkzMQ@@._V1_SX300.jpg", 
    "genre": "Comedy, Romance", 
    "actors": "Cameron Diaz, Kate Winslet, Jude Law, Jack Black", 
    "runtime": "138 min", 
    "type": "movie", 
    "response": "True", 
    "imdb_votes": "184,875"
  }, 
  "29": {
    "plot": "When her brother decides to ditch for a couple weeks in London, Viola heads over to his elite boarding school, disguises herself as him, and proceeds to fall for one of her soccer teammates. Little does she realize she's not the only one with romantic troubles, as she, as he, gets in the middle of a series of intermingled love affairs.", 
    "rated": "PG-13", 
    "language": "English", 
    "title": "She's the Man", 
    "country": "USA, Canada", 
    "writer": "Ewan Leslie (screenplay), Karen McCullah (screenplay), Kirsten Smith (screenplay), Ewan Leslie (story)", 
    "year": "2006", 
    "metascore": "45", 
    "imdb_id": "tt0454945", 
    "director": "Andy Fickman", 
    "released": "17 Mar 2006", 
    "imdb_rating": "6.4", 
    "awards": "2 wins & 5 nominations.", 
    "poster": "https://images-na.ssl-images-amazon.com/images/M/MV5BMjEyMzAzMDk1Ml5BMl5BanBnXkFtZTcwNjg0OTEzMQ@@._V1_SX300.jpg", 
    "genre": "Comedy, Romance, Sport", 
    "actors": "Amanda Bynes, Channing Tatum, Laura Ramsey, Vinnie Jones", 
    "runtime": "105 min", 
    "type": "movie", 
    "response": "True", 
    "imdb_votes": "118,122"
  }
}